PyPulseHeatPipe/__init__.py
PyPulseHeatPipe/php_analysis.py
PyPulseHeatPipe-1.1.13.dist-info/LICENSE
PyPulseHeatPipe-1.1.13.dist-info/METADATA
PyPulseHeatPipe-1.1.13.dist-info/WHEEL
PyPulseHeatPipe-1.1.13.dist-info/top_level.txt
PyPulseHeatPipe-1.1.13.dist-info/RECORD
