Metadata-Version: 2.1
Name: PyPulseHeatPipe
Version: 1.1.13
Summary: The data analysis Python package for the Pulsating Heat Pipe experimental data
Home-page: https://github.com/nirmalparmarphd/PyPulseHeatPipe
Author: Nirmal Parmar, PhD
Author-email: nirmalparmarphd@gmail.com
License: GNU
License-File: LICENSE
Requires-Dist: scikit-learn
Requires-Dist: numpy
Requires-Dist: gitpython
Requires-Dist: pandas
Requires-Dist: scipy
Requires-Dist: matplotlib
Requires-Dist: seaborn
Requires-Dist: openpyxl
Requires-Dist: pygwalker
Requires-Dist: streamlit
